rtmf6/__init__.py
rtmf6/_version.py
rtmf6/main.py
rtmf6-0.0.2.dist-info/METADATA
rtmf6-0.0.2.dist-info/WHEEL
rtmf6-0.0.2.dist-info/entry_points.txt
rtmf6-0.0.2.dist-info/top_level.txt
rtmf6-0.0.2.dist-info/RECORD
