Metadata-Version: 2.1
Name: rtmf6
Version: 0.0.2
Summary: Reactive transport modeling with MODFLOW 6
Author-email: Mike Müller <mmueller@hydrocomputing.com>
License: MIT License
Keywords: MODFLOW6,pymf6,PHREEQC,PhreeqcRM,PhreeqPy,groundwater,modeling,reactive transport
Classifier: Development Status :: 3 - Alpha
Classifier: License :: OSI Approved :: MIT License
Classifier: Programming Language :: Python :: 3
Classifier: Environment :: Console
Classifier: Framework :: Jupyter :: JupyterLab
Classifier: Intended Audience :: Developers
Classifier: Intended Audience :: Science/Research
Classifier: Operating System :: Microsoft :: Windows
Classifier: Operating System :: POSIX
Classifier: Operating System :: MacOS :: MacOS X
Classifier: Programming Language :: Python :: Implementation :: CPython
Classifier: Intended Audience :: Science/Research
Classifier: Topic :: Scientific/Engineering :: Hydrology
Requires-Python: >=3.11
Provides-Extra: test
Requires-Dist: pytest ; extra == 'test'
